Metadata-Version: 2.1
Name: datasette-enrichments-jinja
Version: 0.1
Summary: Datasette enrichment for evaluating templates in a Jinja sandbox
Author: Simon Willison
License: Apache-2.0
Project-URL: Homepage, https://github.com/datasette/datasette-enrichments-jinja
Project-URL: Changelog, https://github.com/datasette/datasette-enrichments-jinja/releases
Project-URL: Issues, https://github.com/datasette/datasette-enrichments-jinja/issues
Project-URL: CI, https://github.com/datasette/datasette-enrichments-jinja/actions
Classifier: Framework :: Datasette
Classifier: License :: OSI Approved :: Apache Software License
Requires-Python: >=3.8
License-File: LICENSE
Requires-Dist: datasette-enrichments >=0.1a4
Provides-Extra: test
Requires-Dist: pytest ; extra == 'test'
Requires-Dist: pytest-asyncio ; extra == 'test'
Requires-Dist: sqlite-utils ; extra == 'test'
